{
  "src:assets/images/cover.avif": "7c6f966a628a816e82",
  "src:assets/images/MobileWallpaper/m6.avif": "a08eaac3abbfc7bdc8",
  "src:assets/images/MobileWallpaper/m5.avif": "af99aecab1c1d2c2cb",
  "src:assets/images/MobileWallpaper/m4.avif": "f0e1e2d4bfc7c2abc1",
  "src:assets/images/MobileWallpaper/m3.avif": "c3a6b4dac2cad2c0c9",
  "src:assets/images/MobileWallpaper/m2.avif": "f1e0ded8c2c6bbb0bc",
  "src:assets/images/MobileWallpaper/m1.avif": "cccce0cbc0d59294c0",
  "public:assets/images/sponsor/wechat.png": "d5d5d5dad9d7dbd8cf",
  "public:assets/images/sponsor/alipay.png": "8ebbde91bedf93c0e0",
  "public:assets/images/ad/ad1.webp": "a1b8b68a8e918c8f93",
  "src:content/posts/images/vitepress.avif": "3d3d43e1e1e7ebe0da",
  "src:content/posts/images/right-grid2.avif": "cbcdcddddcd9d8d7db",
  "src:content/posts/images/obsidian.avif": "3a4145dce3e6e8ded8",
  "src:content/posts/images/masonry.avif": "e4e6e4ecefebd3d1d2",
  "src:content/posts/images/left-list.avif": "e9edeae3e6e3dddde1",
  "src:content/posts/images/left-grid3.avif": "d7d9d9d6daddd8e1e3",
  "src:content/posts/images/github.avif": "3a3a3be6e7e7eae9e9",
  "src:content/posts/images/firefly3.avif": "7c6f966a628a816e81",
  "src:content/posts/images/firefly2.avif": "7588a28a8f989e8d88",
  "src:content/posts/images/firefly1.avif": "d4d7e5cdc4d7baaec9",
  "src:content/posts/images/docusaurus.avif": "445347e2e8e3e8e4dc",
  "src:content/posts/images/both-list.avif": "e5e7e4e6e8e7e3e3e5",
  "src:content/posts/images/both-grid.avif": "d5d6d3e6e7e3d8d9e3",
  "src:content/posts/images/1.avif": "b5b0b3bcb6bbe0e0df",
  "public:gallery/photographic-works/摄影作品 (9).jpg": "70634378654858523b",
  "public:gallery/photographic-works/摄影作品 (8).jpg": "70774e9b9589939190",
  "public:gallery/photographic-works/摄影作品 (7).jpg": "5039244e38215d452d",
  "public:gallery/photographic-works/摄影作品 (6).jpg": "b5b18db1a55daca850",
  "public:gallery/photographic-works/摄影作品 (5).jpg": "60694e40553c2e4732",
  "public:gallery/photographic-works/摄影作品 (4).jpg": "bcc1b4b6c0b44f6368",
  "public:gallery/photographic-works/摄影作品 (3).jpg": "6ba1a0a9c3bc8c9f96",
  "public:gallery/photographic-works/摄影作品 (2).jpg": "121d2f142b42354156",
  "public:gallery/photographic-works/摄影作品 (14).jpg": "5a50405a5b55433f31",
  "public:gallery/photographic-works/摄影作品 (13).jpg": "a6cadfafd1e43f5c6e",
  "public:gallery/photographic-works/摄影作品 (12).jpg": "acbbc6acbec97d95a6",
  "public:gallery/photographic-works/摄影作品 (11).jpg": "6d79326c7b3b5c6f2c",
  "public:gallery/photographic-works/摄影作品 (10).jpg": "97968b8e8e7c5c5d4c",
  "public:gallery/photographic-works/摄影作品 (1).jpg": "7f79747c7e785c5b52",
  "public:gallery/photographic-works/cover.jpg": "5a96c8458abe4b5968",
  "src:assets/images/Yangyang.jpg": "9e9898989596a9abae",
  "src:assets/images/yang.jpg": "93949dacaebe989db1",
  "src:assets/images/xiyun.png": "f0c5f0f3c7e6facbd0",
  "src:content/posts/images/yang1.png": "7b7460ad9c7b79735a",
  "src:content/posts/guide/feibi.png": "71aadaa7c3da90afc8",
  "src:assets/images/DesktopWallpaper/W5.png": "5e4e559c7c8999858e",
  "src:assets/images/DesktopWallpaper/W4.png": "99965ec4bf8cc4b878",
  "src:assets/images/DesktopWallpaper/W3.png": "6575816d7c858b9697",
  "src:assets/images/DesktopWallpaper/W2.png": "7b7460ad9c7b79735a",
  "src:assets/images/DesktopWallpaper/W1.png": "3f46657d7d8b858294"
}